aaxyumath/__init__.py
aaxyumath/core.py
aaxyumath-0.1.dist-info/METADATA
aaxyumath-0.1.dist-info/WHEEL
aaxyumath-0.1.dist-info/top_level.txt
aaxyumath-0.1.dist-info/RECORD
