Metadata-Version: 2.4
Name: aaxyumath
Version: 0.1
Summary: A cool math library by AaxYu
Author: AaxYu
Author-email: legendarykartik777@example.com
Classifier: Programming Language :: Python :: 3
Classifier: License :: OSI Approved :: MIT License
Requires-Python: >=3.6
Dynamic: author
Dynamic: author-email
Dynamic: classifier
Dynamic: requires-python
Dynamic: summary
